pyicapserver.py
pyicapserver-1.1.1.dist-info/LICENSE.md
pyicapserver-1.1.1.dist-info/METADATA
pyicapserver-1.1.1.dist-info/WHEEL
pyicapserver-1.1.1.dist-info/top_level.txt
pyicapserver-1.1.1.dist-info/RECORD
